aiodav/__init__.py
aiodav/client.py
aiodav/exceptions.py
aiodav/urn.py
aiodav/utils.py
aiodav-0.1.14.dist-info/licenses/LICENSE
aiodav-0.1.14.dist-info/METADATA
aiodav-0.1.14.dist-info/WHEEL
aiodav-0.1.14.dist-info/top_level.txt
aiodav-0.1.14.dist-info/RECORD
