Metadata-Version: 2.4
Name: aiodav
Version: 0.1.14
Summary: A Python Async WebDAV Client
Author-email: Jorge Alejandro Jiménez Luna <jorgeajimenezl17@gmail.com>
License: MIT
Project-URL: homepage, https://github.com/jorgeajimenezl/aiodav
Keywords: webdav,client,files,internet,download,upload
Classifier: Intended Audience :: Developers
Classifier: License :: OSI Approved :: MIT License
Classifier: Operating System :: OS Independent
Classifier: Programming Language :: Python
Classifier: Programming Language :: Python :: 3.6
Classifier: Programming Language :: Python :: 3.7
Classifier: Programming Language :: Python :: 3.8
Classifier: Programming Language :: Python :: 3.9
Classifier: Programming Language :: Python :: 3.10
Classifier: Programming Language :: Python :: 3.11
Requires-Python: >=3.6
License-File: LICENSE
Requires-Dist: aiohttp
Requires-Dist: aiofiles
Requires-Dist: faust-cchardet
Requires-Dist: aiodns
Requires-Dist: lxml
Dynamic: license-file
Dynamic: requires-python
